{
	"en":
  [
		[
		  "translation attains its full meaning",
		  "in the realization that",
		  "every evolved language",
		  "can be considered as",
		  "a translation of all the others"
		],
		[
		  "by the relation of languages",
		  "as between media",
		  "of varying densities",
		  "the translatablity of languages",
		  "is established"
		],
		[
		  "translation is removal",
		  "from one language",
		  "into another",
		  "through a continuum",
		  "of transformations"
		],
		[
		  "translation passes through",
		  "continua",
		  "of transformation",
		  "not abstract areas",
		  "of identity and similarity"
		]
  ],
	"de":
	[
		[
			"seine volle bedeutung gewinnt er",
			"in der einsicht",
			"daß jede höhere sprache",
			"als übersetzung aller anderen",
			"betrachtet werden kann"
		],
		[
			"mit dem erwähnten verhältnis",
			"der sprache als dem von medien",
			"verschiedener dichte ist",
			"die übersetzbarkeit de sprachen",
			"ineinander gegeben"
		],
		[
			"die übersetzung ist die",
			"überführung der einen sprache",
			"in die andere",
			"durch ein kontinuum",
			"von verwandlungen"
		],
		[
			"kontinua der verwandlung",
			"nicht abstrakte gleischheits",
			"und ähnlichkeitsbezirke",
			"durchmißt",
			"die übersetzung"
		]
	],
	"fr":
	[
		[
			"on n’en saisit la pleine signification",
			"qu’en voyant que",
			"tout langage supérieur",
			"peut être considéré comme",
			"traduction de tous les autres"
		],
		[
			"grâce au rapport entre les langages",
			"comme dépendant de",
			"la densité diverse des média",
			"tous les langages sont traduisibles",
			"les uns dans les autres"
		],
		[
			"la traduction est le passage",
			"d’un langage",
			"dans un autre",
			"par une série",
			"de métamorphoses continues"
		],
		[
			"la traduction parcourt",
			"en les traversant des continus",
			"de métamorphoses",
			"non des régions abstraites",
			"de similitude et de ressemblance"
		]
	],
	"dp":
	[
		[
			"wirklichheit sich nur",
			"der erinnerung formt",
			"jedenfalls kommen mir blummen",
			"die man mir heute zeigt",
			"nicht mehr wie richtige blummen vor"
		],
		[
			"die kornblummen  der weißdorn  weil",
			"sie auf der gleichen höhe oder tiefe",
			"mit meiner vergangenheit gelegen sind",
			"sofort mit meinem herzen",
			"eine verbindung an"
		],
		[
			"würde es nicht genügen",
			"daß man mich an das ufer",
			"eines flusses führte",
			"wo es ebenso schöne seerosen",
			"jene angst in die liebe übergeht"
		],
		[
			"was ich wiedersehen will die wirkliche",
			"gegend die ich gekannt habe",
			"deren ganz persönliche art",
			"phantastisch machtvoll umfängt",
			"und die ich nicht wiederfinden kann"
		]
	],
	"fp":
	[
		[
			"réalité ne se forme que dans la memoire",
			"les fleurs qu’on me montre aujourd’hui",
			"pour la première fois",
			"ne me semblent pas",
			"de vraies fleurs"
		],
		[
			"les bluets  les aubépines  parce qu’ils",
			"sont situés à la même profondeur",
			"au niveau de mon passé",
			"sont immédiatement en communication",
			"avec mon coeur"
		],
		[
			"on ne le satisferait pas",
			"en me menant au bord d’une rivière",
			"où il y aurait",
			"d’aussi beaux nymphéas",
			"angoisse qui émigre dans l’amour"
		],
		[
			"ce que je veux revoir",
			"c’est le côté que j’ai connu",
			"c’est ce paysage dont l’individualité",
			"étreint avec une puissance fantastique",
			"et que je ne peux plus retrouver"
		]
	],
	"ep":
	[
		[
			"reality takes shape only in memory",
			"the flowers i am shown today",
			"for the first time",
			"do not seem to me to be",
			"real flowers"
		],
		[
			"the cornflowers  the hawthorns  because",
			"they are situated at the same depth",
			"on the level of my past",
			"communicate immediately",
			"with my heart"
		],
		[
			"you would not satisfy it",
			"by taking me to the bank of a river",
			"where the water lilies",
			"were just as beautiful",
			"that anguish which emigrates into love"
		],
		[
			"what i want to see again",
			"is the way that i knew",
			"that landscape whose individuality",
			"clasps me with an uncanny power",
			"and which i can no longer recover"
		]
	]
}
